nonebot/adapters/ntchat/__init__.py
nonebot/adapters/ntchat/adapter.py
nonebot/adapters/ntchat/bot.py
nonebot/adapters/ntchat/collator.py
nonebot/adapters/ntchat/config.py
nonebot/adapters/ntchat/event.py
nonebot/adapters/ntchat/exception.py
nonebot/adapters/ntchat/message.py
nonebot/adapters/ntchat/permission.py
nonebot/adapters/ntchat/store.py
nonebot/adapters/ntchat/type.py
nonebot/adapters/ntchat/utils.py
nonebot_adapter_ntchat-0.3.5.dist-info/LICENSE
nonebot_adapter_ntchat-0.3.5.dist-info/METADATA
nonebot_adapter_ntchat-0.3.5.dist-info/WHEEL
nonebot_adapter_ntchat-0.3.5.dist-info/top_level.txt
nonebot_adapter_ntchat-0.3.5.dist-info/RECORD
