Metadata-Version: 2.1
Name: nonebot-adapter-ntchat
Version: 0.3.5
Summary: a wechat adapter for nonebot2
Home-page: https://github.com/JustUndertaker/adapter-ntchat
Author: JustUndertaker
Author-email: 806792561@qq.com
Classifier: Programming Language :: Python :: 3.8
Classifier: Programming Language :: Python :: 3.9
Classifier: Programming Language :: Python :: 3.10
Classifier: License :: OSI Approved :: MIT License
Requires-Python: >=3.8
License-File: LICENSE
Requires-Dist: httpx (==0.23.0)
